paramonte/_AutoCorr.py
paramonte/_CorCovMat.py
paramonte/_OutputFileContents.py
paramonte/_ParaMonteSampler.py
paramonte/_ReportFileContents.py
paramonte/_RestartFileContents.py
paramonte/_SpecBase.py
paramonte/_SpecDRAM.py
paramonte/_SpecMCMC.py
paramonte/_TabularFileContents.py
paramonte/_Version.py
paramonte/__init__.py
paramonte/_dfutils.py
paramonte/_message.py
paramonte/_paradram.py
paramonte/_paramonte.py
paramonte/_pmreqs.py
paramonte/_pmutils.py
paramonte/mvn.py
paramonte/auxil/.ParaMonteBanner
paramonte/auxil/.VERSION_INTERFACE
paramonte/auxil/.VERSION_KERNEL
paramonte/auxil/.dependencies_linux
paramonte/auxil/.dependencies_windows
paramonte/auxil/.mpivarsPath
paramonte/auxil/.verificationEnabled
paramonte/lib/x64/gnu/libgcc_s.1.dylib
paramonte/lib/x64/gnu/libgcc_s.so.1
paramonte/lib/x64/gnu/libgfortran.5.dylib
paramonte/lib/x64/gnu/libgfortran.so.5
paramonte/lib/x64/gnu/libmpi.12.dylib
paramonte/lib/x64/gnu/libmpi.40.dylib
paramonte/lib/x64/gnu/libmpi_mpifh.40.dylib
paramonte/lib/x64/gnu/libmpi_usempi_ignore_tkr.40.dylib
paramonte/lib/x64/gnu/libmpi_usempif08.40.dylib
paramonte/lib/x64/gnu/libmpifort.12.dylib
paramonte/lib/x64/gnu/libparamonte_python_darwin_x64_gnu_debug_shared_heap.dylib
paramonte/lib/x64/gnu/libparamonte_python_darwin_x64_gnu_debug_shared_heap_mpich.dylib
paramonte/lib/x64/gnu/libparamonte_python_darwin_x64_gnu_debug_shared_heap_openmpi.dylib
paramonte/lib/x64/gnu/libparamonte_python_darwin_x64_gnu_release_shared_heap.dylib
paramonte/lib/x64/gnu/libparamonte_python_darwin_x64_gnu_release_shared_heap_mpich.dylib
paramonte/lib/x64/gnu/libparamonte_python_darwin_x64_gnu_release_shared_heap_openmpi.dylib
paramonte/lib/x64/gnu/libparamonte_python_linux_x64_gnu_debug_shared_heap.so
paramonte/lib/x64/gnu/libparamonte_python_linux_x64_gnu_debug_shared_heap_mpich.so
paramonte/lib/x64/gnu/libparamonte_python_linux_x64_gnu_debug_shared_heap_openmpi.so
paramonte/lib/x64/gnu/libparamonte_python_linux_x64_gnu_release_shared_heap.so
paramonte-2.5.2.dist-info/LICENSE.md
paramonte-2.5.2.dist-info/METADATA
paramonte-2.5.2.dist-info/WHEEL
paramonte-2.5.2.dist-info/top_level.txt
paramonte-2.5.2.dist-info/RECORD
