Metadata-Version: 2.1
Name: paramonte
Version: 2.5.2
Summary: Plain Powerful Parallel Monte Carlo and adaptive MCMC Library
Home-page: https://github.com/cdslaborg/paramonte
Author: Amir Shahmoradi, Fatemeh Bagheri, Joshua Alexander Osborne
Author-email: shahmoradi@utexas.edu
License: License :: OSI Approved :: MIT License
Platform: UNKNOWN
Classifier: Development Status :: 5 - Production/Stable
Classifier: Natural Language :: English
Classifier: Programming Language :: Python :: 3
Classifier: Programming Language :: Fortran
Classifier: Programming Language :: C
Classifier: License :: OSI Approved :: MIT License
Classifier: Operating System :: OS Independent
Classifier: Topic :: Scientific/Engineering
Classifier: Topic :: Scientific/Engineering :: Physics
Classifier: Topic :: Scientific/Engineering :: Astronomy
Classifier: Topic :: Scientific/Engineering :: Mathematics
Classifier: Topic :: Scientific/Engineering :: Visualization
Classifier: Topic :: Scientific/Engineering :: Bio-Informatics
Classifier: Topic :: Scientific/Engineering :: Atmospheric Science
Classifier: Operating System :: OS Independent
Classifier: Operating System :: Microsoft :: Windows
Classifier: Operating System :: POSIX :: Linux
Classifier: Operating System :: MacOS
Classifier: Operating System :: Unix
Requires-Python: >=3.0
Requires-Dist: numpy
Requires-Dist: pandas
